SeaSmartApiClient/__init__.py
SeaSmartApiClient/api.py
SeaSmartApiClient/error.py
seasmart_python_api_client-0.1.4.dist-info/LICENSE
seasmart_python_api_client-0.1.4.dist-info/METADATA
seasmart_python_api_client-0.1.4.dist-info/WHEEL
seasmart_python_api_client-0.1.4.dist-info/top_level.txt
seasmart_python_api_client-0.1.4.dist-info/RECORD
