Metadata-Version: 2.1
Name: seasmart-python-api-client
Version: 0.1.4
Summary: A Python client for the SeaSmart API.
Home-page: https://github.com/SeaSmart/seasmart-python-api-client
Author: Bradley Wogsland
Author-email: bradley@wogsland.org
License: UNKNOWN
Keywords: SeaSmart aquaculture IoT
Platform: Any
Classifier: Intended Audience :: Developers
Classifier: Operating System :: OS Independent
Classifier: Topic :: Software Development :: Libraries :: Python Modules
Classifier: Programming Language :: Python
Classifier: Programming Language :: Python :: 2
Classifier: Programming Language :: Python :: 2.7
Classifier: Programming Language :: Python :: 3
Classifier: Programming Language :: Python :: 3.5
Classifier: Programming Language :: Python :: 3.6
Classifier: Programming Language :: Python :: 3.7
Classifier: Programming Language :: Python :: 3.8
Requires-Dist: requests
